argparse_tree/Atree.py
argparse_tree/__init__.py
argparse_tree/load_module_action.py
argparse_tree/store_action.py
argparse_tree/sub_parsers_action.py
argparse_tree/utils.py
argparse_tree-0.1.3.post6.dist-info/LICENSE
argparse_tree-0.1.3.post6.dist-info/METADATA
argparse_tree-0.1.3.post6.dist-info/WHEEL
argparse_tree-0.1.3.post6.dist-info/top_level.txt
argparse_tree-0.1.3.post6.dist-info/RECORD
