Metadata-Version: 2.1
Name: argparse-tree
Version: 0.1.3.post6
Summary: Split parse args into filesystem tree for complex projects.
Home-page: https://github.com/bvraghav/argparse_tree
Author: B.V. Raghav
License: MIT
Platform: UNKNOWN
Classifier: Programming Language :: Python :: 3
Classifier: License :: OSI Approved :: MIT License
Classifier: Operating System :: OS Independent
Requires-Python: >=3
